eyes17/Peripherals.py
eyes17/__init__.py
eyes17/achan.py
eyes17/commands_proto.py
eyes17/eyemath17.py
eyes17/eyeplot17.py
eyes17/eyes.py
eyes17/packet_handler.py
eyes17/sensorlist.py
eyes17/stepperA4988.py
eyes17/wifi_packet_handler.py
eyes17/wifi_packet_handler_udp.py
eyes17/wifi_packet_handler_udp_backup.py
eyes17/SENSORS/AD7718_class.py
eyes17/SENSORS/AD9833.py
eyes17/SENSORS/ADS1115.py
eyes17/SENSORS/ADS1248.py
eyes17/SENSORS/ALLSENSORS.py
eyes17/SENSORS/BH1750.py
eyes17/SENSORS/BMP180.py
eyes17/SENSORS/BMP280.py
eyes17/SENSORS/ComplementaryFilter.py
eyes17/SENSORS/HMC5883L.py
eyes17/SENSORS/Kalman.py
eyes17/SENSORS/MF522.py
eyes17/SENSORS/MLX90614.py
eyes17/SENSORS/MPU6050.py
eyes17/SENSORS/MPU925x.py
eyes17/SENSORS/PCF_LCD.py
eyes17/SENSORS/QMC5883L.py
eyes17/SENSORS/SHT21.py
eyes17/SENSORS/SSD1306.py
eyes17/SENSORS/TDC7200.py
eyes17/SENSORS/TSL2561.py
eyes17/SENSORS/TSL2591.py
eyes17/SENSORS/VL53L01X.py
eyes17/SENSORS/__init__.py
eyes17/SENSORS/supported.py
resources/99-eyes17-pip.rules
resources/__init__.py
resources/sispmctl.conf
eyes17lib-1.2.4.dist-info/LICENSE
eyes17lib-1.2.4.dist-info/METADATA
eyes17lib-1.2.4.dist-info/WHEEL
eyes17lib-1.2.4.dist-info/top_level.txt
eyes17lib-1.2.4.dist-info/RECORD
